Workbook

Sheet SalesData
A1: EmployeeID | B1: EmployeeName | C1: City | D1: Region | E1: Category | F1: Product | G1: UnitsSold | H1: UnitPrice | I1: SaleDate | J1: Revenue | K1: EmployeeCode
A2: 101 | B2: Anita Rao | C2: Bangalore | D2: South | E2: Electronics | F2: Laptop | G2: 3 | H2: 55000 | I2: 46034 | J2: 165000 | K2: EMP-BLR-101
A3: 102 | B3: Karthik S | C3: Chennai | D3: South | E3: Furniture | F3: Office Chair | G3: 8 | H3: 6500 | I3: 46037 | J3: 52000 | K3: EMP-CHE-102
A4: 103 | B4: Meena K | C4: Hyderabad | D4: South | E4: Electronics | F4: Monitor | G4: 5 | H4: 12000 | I4: 46056 | J4: 60000 | K4: EMP-HYD-103
A5: 104 | B5: Rahul P | C5: Mumbai | D5: West | E5: Accessories | F5: Keyboard | G5: 12 | H5: 1200 | I5: 46063 | J5: 14400 | K5: EMP-MUM-104
A6: 105 | B6: Priya N | C6: Bangalore | D6: South | E6: Electronics | F6: Laptop | G6: 2 | H6: 55000 | I6: 46071 | J6: 110000 | K6: EMP-BLR-105
A7: 106 | B7: Arjun M | C7: Pune | D7: West | E7: Furniture | F7: Office Chair | G7: 6 | H7: 6500 | I7: 46082 | J7: 39000 | K7: EMP-PUN-106
A8: 107 | B8: Divya R | C8: Chennai | D8: South | E8: Accessories | F8: Mouse | G8: 20 | H8: 750 | I8: 46090 | J8: 15000 | K8: EMP-CHE-107
A9: 108 | B9: Vikram T | C9: Mumbai | D9: West | E9: Electronics | F9: Monitor | G9: 4 | H9: 12000 | I9: 46095 | J9: 48000 | K9: EMP-MUM-108
A10: 109 | B10: Sneha V | C10: Hyderabad | D10: South | E10: Furniture | F10: Office Desk | G10: 2 | H10: 18000 | I10: 46114 | J10: 36000 | K10: EMP-HYD-109
A11: 110 | B11: Naveen G | C11: Bangalore | D11: South | E11: Accessories | F11: Keyboard | G11: 10 | H11: 1200 | I11: 46123 | J11: 12000 | K11: EMP-BLR-110
A12: 111 | B12: Farah A | C12: Pune | D12: West | E12: Electronics | F12: Laptop | G12: 1 | H12: 55000 | I12: 46132 | J12: 55000 | K12: EMP-PUN-111
A13: 112 | B13: Sanjay L | C13: Chennai | D13: South | E13: Furniture | F13: Office Desk | G13: 3 | H13: 18000 | I13: 46147 | J13: 54000 | K13: EMP-CHE-112

Sheet Sheet2
A1: EmployeeID | B1: EmployeeName | C1: City | D1: Region | E1: Product | F1: UnitsSold | G1: UnitPrice | H1: Category
A2: 101 | B2: Anita Rao | C2: Bangalore | D2: South | E2: Laptop | F2: 3 | G2: =VLOOKUP(A2,SalesData!A:K,8,0) -> 55000 | H2: =VLOOKUP(A2,SalesData!A:H,5,0) -> Electronics
A3: 102 | B3: Karthik S | C3: Chennai | D3: South | E3: Office Chair | F3: 8 | G3: =VLOOKUP(A3,SalesData!A:K,8,0) -> 6500 | H3: =VLOOKUP(A3,SalesData!A:H,5,0) -> Furniture
A4: 103 | B4: Meena K | C4: Hyderabad | D4: South | E4: Monitor | F4: 5 | G4: =VLOOKUP(A4,SalesData!A:K,8,0) -> 12000 | H4: =VLOOKUP(A4,SalesData!A:H,5,0) -> Electronics
A5: 104 | B5: Rahul P | C5: Mumbai | D5: West | E5: Keyboard | F5: 12 | G5: =VLOOKUP(A5,SalesData!A:K,8,0) -> 1200 | H5: =VLOOKUP(A5,SalesData!A:H,5,0) -> Accessories
A6: 105 | B6: Priya N | C6: Bangalore | D6: South | E6: Laptop | F6: 2 | G6: =VLOOKUP(A6,SalesData!A:K,8,0) -> 55000 | H6: =VLOOKUP(A6,SalesData!A:H,5,0) -> Electronics
A7: 106 | B7: Arjun M | C7: Pune | D7: West | E7: Office Chair | F7: 6 | G7: =VLOOKUP(A7,SalesData!A:K,8,0) -> 6500 | H7: =VLOOKUP(A7,SalesData!A:H,5,0) -> Furniture
A8: 107 | B8: Divya R | C8: Chennai | D8: South | E8: Mouse | F8: 20 | G8: =VLOOKUP(A8,SalesData!A:K,8,0) -> 750 | H8: =VLOOKUP(A8,SalesData!A:H,5,0) -> Accessories
A9: 111 | B9: Farah A | C9: Pune | D9: West | E9: Laptop | F9: 1 | G9: =VLOOKUP(A9,SalesData!A:K,8,0) -> 55000 | H9: =VLOOKUP(A9,SalesData!A:H,5,0) -> Electronics
A10: 112 | B10: Sanjay L | C10: Chennai | D10: South | E10: Office Desk | F10: 3 | G10: =VLOOKUP(A10,SalesData!A:K,8,0) -> 18000 | H10: =VLOOKUP(A10,SalesData!A:H,5,0) -> Furniture
A11: 108 | B11: Vikram T | C11: Mumbai | D11: West | E11: Monitor | F11: 4 | G11: =VLOOKUP(A11,SalesData!A:K,8,0) -> 12000 | H11: =VLOOKUP(A11,SalesData!A:H,5,0) -> Electronics
A12: 109 | B12: Sneha V | C12: Hyderabad | D12: South | E12: Office Desk | F12: 2 | G12: =VLOOKUP(A12,SalesData!A:K,8,0) -> 18000 | H12: =VLOOKUP(A12,SalesData!A:H,5,0) -> Furniture

Sheet Products
A1: Product | B1: Category | C1: UnitPrice | D1: PriceBand
A2: Laptop | B2: Electronics | C2: 55000 | D2: Premium
A3: Monitor | B3: Electronics | C3: 12000 | D3: Standard
A4: Office Chair | B4: Furniture | C4: 6500 | D4: Standard
A5: Office Desk | B5: Furniture | C5: 18000 | D5: Premium
A6: Keyboard | B6: Accessories | C6: 1200 | D6: Basic
A7: Mouse | B7: Accessories | C7: 750 | D7: Basic

Sheet VLOOKUP_MISMATCH
A1: Product | B1: Category | C1: UnitPrice | D1: PriceBand | E1: Revenue
A2: Laptop | B2: Electronics | C2: 55000 | D2: =VLOOKUP(A2,Products!A:D,4,0) -> Premium | E2: =VLOOKUP(A2,SalesData!F:J,5,0) -> 165000
A3: Monitor | B3: Electronics | C3: 12000 | D3: =VLOOKUP(A3,Products!A:D,4,0) -> Standard | E3: =VLOOKUP(A3,SalesData!F:J,5,0) -> 60000
A4: Keyboard | B4: Accessories | C4: 1200 | D4: =VLOOKUP(A4,Products!A:D,4,0) -> Basic | E4: =VLOOKUP(A4,SalesData!F:J,5,0) -> 14400
A5: Office Chair | B5: Furniture | C5: 6500 | D5: =VLOOKUP(A5,Products!A:D,4,0) -> Standard | E5: =VLOOKUP(A5,SalesData!F:J,5,0) -> 52000

Sheet Questions_Answers
A1: Function | B1: Practice Question | C1: Formula (enter in Excel) | D1: Expected Answer
A2: SUMIF | B2: Find total revenue for the South region. | D2: 504000
A3: SUMIF | B3: Find total revenue for Electronics category. | D3: 438000
A4: SUMIFS | B4: Find revenue for South region and Electronics category. | D4: 335000
A5: SUMIFS | B5: Find revenue for Bangalore city and sales of at least 3 units. | D5: 177000
A6: COUNTIF | B6: Count how many sales records are from Chennai. | D6: 3
A7: COUNTIF | B7: Count how many sales records have more than 5 units sold. | D7: 5
A8: COUNTIFS | B8: Count Electronics sales in the South region. | D8: 3
A9: COUNTIFS | B9: Count records where the city is Bangalore and units sold are at least 3. | D9: 2
A10: MID | B10: Extract the 3-letter city code from EMP-BLR-101 (EmployeeCode in L2). | D10: BLR
A11: CONCAT | B11: Combine EmployeeName and City with a hyphen. | D11: Anita Rao - Bangalore
A12: CONCATENATE | B12: Create a label like Anita Rao (EMP-BLR-101). | D12: Anita Rao (EMP-BLR-101)
A13: SUM | B13: Calculate total revenue. | D13: 660400
A14: AVERAGE | B14: Calculate average revenue per sales record. | D14: 55033.33
A15: MAX | B15: Find the highest revenue in one sales record. | D15: 165000
A16: MIN | B16: Find the lowest revenue in one sales record. | D16: 12000
A17: COUNT | B17: Count numeric values in UnitsSold. | D17: 12
A18: COUNTA | B18: Count non-empty employee names. | D18: 12
A19: SUBTOTAL | B19: Calculate total revenue while excluding filtered-out rows. | D19: 660400
A20: VLOOKUP | B20: Look up the category for the product in F2 using the Products sheet. | D20: Electronics
A21: VLOOKUP | B21: Look up the price band for the product in F2 using the Products sheet. | D21: Premium
A22: XLOOKUP | B22: Look up the unit price for the product in F2 using the Products sheet. | D22: 55000
A23: XLOOKUP | B23: Return the employee name for EmployeeID 108. | D23: Vikram T
A25: Item | B25: Time Taken
A26: Bread | B26: 2
A27: Cake | B27: 1
A28: Biscuits | B28: 2
A29: 1.How much profit we can get maximum Profit in 8hrs(closing time still we have 8hrs)
A32: X(Bread) | B32: 0
A33: Y(Cake) | B33: 0
A34: Z(Biscuits) | B34: 4
A36: Total Profit | B36: =C26*B32+C27*B33+C28*B34 -> 0
A37: Total Time | B37: =B26*B32+B27*B33+B28*B34 -> 8
